unidas.py
unidas-0.0.1.dist-info/METADATA
unidas-0.0.1.dist-info/WHEEL
unidas-0.0.1.dist-info/licenses/LICENSE
unidas-0.0.1.dist-info/RECORD
