Metadata-Version: 2.4
Name: unidas
Version: 0.0.1
Summary: A DAS compatibility library
Project-URL: Bug Tracker, https://github.com/unidas-dev/unidas
Project-URL: Documentation, https://github.com/unidas-dev/unidas
Project-URL: Homepage, https://github.com/unidas-dev/unidas
Author-email: Derrick Chambers <chambers.ja.derrick@gmail.com>
License-File: LICENSE
Keywords: distributed-acoustic-sensing,geophysics
Classifier: License :: OSI Approved :: MIT License
Classifier: Topic :: Scientific/Engineering
Requires-Python: >=3.10
Requires-Dist: numpy
Provides-Extra: dev
Requires-Dist: dascore; extra == 'dev'
Requires-Dist: daspy-toolbox; extra == 'dev'
Requires-Dist: lightguide; extra == 'dev'
Requires-Dist: numpy<2; extra == 'dev'
Requires-Dist: pooch; extra == 'dev'
Requires-Dist: pre-commit; extra == 'dev'
Requires-Dist: pytest; extra == 'dev'
Requires-Dist: pytest-cov; extra == 'dev'
Requires-Dist: ruff; extra == 'dev'
Requires-Dist: xdas; extra == 'dev'
Provides-Extra: extras
Requires-Dist: dascore; extra == 'extras'
Requires-Dist: daspy-toolbox; extra == 'extras'
Requires-Dist: lightguide; extra == 'extras'
Requires-Dist: numpy<2; extra == 'extras'
Requires-Dist: xdas; extra == 'extras'
Provides-Extra: test
Requires-Dist: pooch; extra == 'test'
Requires-Dist: pre-commit; extra == 'test'
Requires-Dist: pytest; extra == 'test'
Requires-Dist: pytest-cov; extra == 'test'
Requires-Dist: ruff; extra == 'test'
